langevals_huggingface/llama_guard.py
langevals_huggingface-0.1.12.dist-info/METADATA
langevals_huggingface-0.1.12.dist-info/WHEEL
langevals_huggingface-0.1.12.dist-info/RECORD
