Metadata-Version: 2.4
Name: langevals-huggingface
Version: 0.1.12
Summary: Evaluators based on models available on huggingface.
License: MIT
Author: Rogerio Chaves
Author-email: rogerio@langwatch.ai
Requires-Python: >=3.11,<4.0
Classifier: License :: OSI Approved :: MIT License
Classifier: Programming Language :: Python :: 3
Classifier: Programming Language :: Python :: 3.11
Classifier: Programming Language :: Python :: 3.12
Classifier: Programming Language :: Python :: 3.13
Classifier: Programming Language :: Python :: 3.14
Requires-Dist: httpx (>=0.27.0,<0.28.0)
Requires-Dist: langevals-core (>=0.1.18,<0.2.0)
Requires-Dist: litellm (==1.76.0)
